PyHand_Earth/README.md
PyHand_Earth/__init__.py
PyHand_Earth/capture_thread.py
PyHand_Earth/capture_window.py
PyHand_Earth/command_thread.py
PyHand_Earth/file_download.py
PyHand_Earth/google_earth.py
PyHand_Earth/keyboard_commands.py
PyHand_Earth/main_qt.py
PyHand_Earth/requirements.txt
PyHand_Earth/images/click.png
PyHand_Earth/images/clicked_sidebar.png
PyHand_Earth/images/close.png
PyHand_Earth/images/fist.png
PyHand_Earth/images/five_wide.png
PyHand_Earth/images/fullscreen.png
PyHand_Earth/images/index_up.png
PyHand_Earth/images/palm.png
PyHand_Earth/images/shaka.png
PyHand_Earth/images/thumb_left.png
PyHand_Earth/images/thumb_right.png
PyHand_Earth/images/unclicked_sidebar.png
PyHand_Earth/images/v_sign.png
PyHand_Earth-1.1.0.dist-info/LICENSE
PyHand_Earth-1.1.0.dist-info/METADATA
PyHand_Earth-1.1.0.dist-info/WHEEL
PyHand_Earth-1.1.0.dist-info/entry_points.txt
PyHand_Earth-1.1.0.dist-info/top_level.txt
PyHand_Earth-1.1.0.dist-info/RECORD
